{
   "attribute": {
      "chandas": "",
      "devata": "",
      "rishi": ""
   },
   "classification": {
      "anuvakkam": 3,
      "kanda": 4,
      "panchasat": 1,
      "prasna": 5
   },
   "ghanapaatha": {
      "lines": [
         "नमः॒ सह॑मानाय॒ सह॑मानाय॒ नमो॒ नमः॒ सह॑मानाय निव्या॒धिने॑ निव्या॒धिने॒ सह॑मानाय॒ नमो॒ नमः॒ सह॑मानाय निव्या॒धिने᳚ ।",
         "सह॑मानाय निव्या॒धिने॑ निव्या॒धिने॒ सह॑मानाय॒ सह॑मानाय निव्या॒धिन॑ आव्या॒धिनी॑ना माव्या॒धिनी॑नां निव्या॒धिने॒ सह॑मानाय॒ सह॑मानाय निव्या॒धिन॑ आव्या॒धिनी॑नाम् ।",
         "नि॒व्या॒धिन॑ आव्या॒धिनी॑ना माव्या॒धिनी॑नां निव्या॒धिने॑ निव्या॒धिन॑ आव्या॒धिनी॑ना॒म् पत॑ये॒ पत॑य आव्या॒धिनी॑नां निव्या॒धिने॑ निव्या॒धिन॑ आव्या॒धिनी॑ना॒म् पत॑ये ।",
         "नि॒व्या॒धिन॒ इति॑ नि - व्या॒धिने᳚ ।",
         "आ॒व्या॒धिनी॑ना॒म् पत॑ये॒ पत॑य आव्या॒धिनी॑ना माव्या॒धिनी॑ना॒म् पत॑ये॒ नमो॒ नम॒ स्पत॑य आव्या॒धिनी॑ना माव्या॒धिनी॑ना॒म् पत॑ये॒ नमः॑ ।",
         "आ॒व्या॒धिनी॑ना॒मित्या᳚ - व्या॒धिनी॑नाम् ।",
         "पत॑ये॒ नमो॒ नम॒ स्पत॑ये॒ पत॑ये॒ नमो॒ नमः॑ ।",
         "नमो॒ नमः॑ ।",
         "नमः॑ ककु॒भाय॑ ककु॒भाय॒ नमो॒ नमः॑ ककु॒भाय॑ निष॒ङ्गिणे॑ निष॒ङ्गिणे॑ ककु॒भाय॒ नमो॒ नमः॑ ककु॒भाय॑ निष॒ङ्गिणे᳚ ।",
         "क॒कु॒भाय॑ निष॒ङ्गिणे॑ निष॒ङ्गिणे॑ ककु॒भाय॑ ककु॒भाय॑ निष॒ङ्गिणे᳚ स्ते॒नानाꣳ॑ स्ते॒नाना᳚न्निष॒ङ्गिणे॑ ककु॒भाय॑ ककु॒भाय॑ निष॒ङ्गिणे᳚ स्ते॒नाना᳚म् ।",
         "नि॒ष॒ङ्गिणे᳚ स्ते॒नानाꣳ॑ स्ते॒नाना᳚म् निष॒ङ्गिणे॑ निष॒ङ्गिणे᳚ स्ते॒नाना॒म् पत॑ये॒ पत॑ये \nस्ते॒नाना᳚म् निष॒ङ्गिणे॑ निष॒ङ्गिणे᳚ स्ते॒नाना॒म् पत॑ये ।",
         "नि॒ष॒ङ्गिण॒ इति॑ नि - स॒ङ्गिने᳚ ।",
         "स्ते॒नाना॒म् पत॑ये॒ पत॑ये स्ते॒नानाꣳ॑ स्ते॒नाना॒म् पत॑ये॒ नमो॒ नम॒ स्पत॑ये स्ते॒नानाꣳ॑ स्ते॒नाना॒म् पत॑ये॒ नमः॑ ।",
         "पत॑ये॒ नमो॒ नम॒ स्पत॑ये॒ पत॑ये॒ नमो॒ नमः॑ ।",
         "नमो॒ नमः॑ ।",
         "नमो॑ निष॒ङ्गिणे॑ निष॒ङ्गिणे॒ नमो॒ नमो॑ निष॒ङ्गिण॑ इषुधि॒मत॑ इषुधि॒मते॑ निष॒ङ्गिणे॒ नमो॒ नमो॑ निष॒ङ्गिण॑ इषुधि॒मते᳚ ।",
         "नि॒ष॒ङ्गिण॑ इषुधि॒मत॑ इषुधि॒मते॑ निष॒ङ्गिणे॑ निष॒ङ्गिण॑ इषुधि॒मते॒ तस्क॑राणा॒म् तस्क॑राणा मिषुधि॒मते॑ निष॒ङ्गिणे॑ निष॒ङ्गिण॑ इषुधि॒मते॒ तस्क॑राणाम् ।",
         "नि॒ष॒ङ्गिण॒ इति॑ नि - स॒ङ्गिने᳚ ।",
         "इ॒षु॒धि॒मते॒ तस्क॑राणा॒म् तस्क॑राणा मिषुधि॒मत॑ इषुधि॒मते॒ तस्क॑राणा॒म् पत॑ये॒ पत॑ये॒ तस्क॑राणा मिषुधि॒मत॑ इषुधि॒मते॒ तस्क॑राणा॒म् पत॑ये ।",
         "इ॒षु॒धि॒मत॒ इती॑षुधि - मते᳚ ।",
         "तस्क॑राणा॒म् पत॑ये॒ पत॑ये॒ तस्क॑राणा॒म् तस्क॑राणा॒म् पत॑ये॒ नमो॒ नम॒ स्पत॑ये॒ तस्क॑राणा॒म् तस्क॑राणा॒म् पत॑ये॒ नमः॑ ।",
         "पत॑ये॒ नमो॒ नम॒ स्पत॑ये॒ पत॑ये॒ नमो॒ नमः॑ ।",
         "नमो॒ नमः॑ ।",
         "नमो॒ वञ्च॑ते॒ वञ्च॑ते॒ नमो॒ नमो॒ वञ्च॑ते परि॒वञ्च॑ते परि॒वञ्च॑ते॒ वञ्च॑ते॒ नमो॒ नमो॒ वञ्च॑ते परि॒वञ्च॑ते ।",
         "वञ्च॑ते परि॒वञ्च॑ते परि॒वञ्च॑ते॒ वञ्च॑ते॒ वञ्च॑ते परि॒वञ्च॑ते स्तायू॒नाꣳ स्ता॑यू॒नाम् प॑रि॒वञ्च॑ते॒ वञ्च॑ते॒ वञ्च॑ते परि॒वञ्च॑ते स्तायू॒नाम् ।",
         "प॒रि॒वञ्च॑ते स्तायू॒नाꣳ स्ता॑यू॒नाम् प॑रि॒वञ्च॑ते परि॒वञ्च॑ते स्तायू॒नाम् पत॑ये॒ पत॑ये स्तायू॒नाम् प॑रि॒वञ्च॑ते परि॒वञ्च॑ते स्तायू॒नाम् पत॑ये ।",
         "प॒रि॒वञ्च॑त॒ इति॑ परि - वञ्च॑ते ।",
         "स्ता॒यू॒नाम् पत॑ये॒ पत॑ये स्तायू॒नाꣳ स्ता॑यू॒नाम् पत॑ये॒ नमो॒ नम॒ स्पत॑ये स्तायू॒नाꣳ स्ता॑यू॒नाम् पत॑ये॒ नमः॑ ।",
         "पत॑ये॒ नमो॒ नम॒ स्पत॑ये॒ पत॑ये॒ नमो॒ नमः॑ ।",
         "नमो॒ नमः॑ ।",
         "नमो॑ निचे॒रवे॑ निचे॒रवे॒ नमो॒ नमो॑ निचे॒रवे॑ परिच॒राय॑ परिच॒राय॑ निचे॒रवे॒ नमो॒ नमो॑ निचे॒रवे॑ परिच॒राय॑ ।",
         "नि॒चे॒रवे॑ परिच॒राय॑ परिच॒राय॑ निचे॒रवे॑ निचे॒रवे॑ परिच॒राया र॑ण्याना॒ मर॑ण्यानाम् परिच॒राय॑ निचे॒रवे॑ निचे॒रवे॑ परिच॒राया र॑ण्यानाम् ।",
         "नि॒चे॒रव॒ इति॑ नि - चे॒रवे᳚ ।",
         "प॒रि॒च॒राया र॑ण्याना॒ मर॑ण्यानाम् परिच॒राय॑ परिच॒राया र॑ण्याना॒म् पत॑ये॒ पत॒ये ऽर॑ण्यानाम् परिच॒राय॑ परिच॒राया र॑ण्याना॒म् पत॑ये ।",
         "प॒रि॒च॒रायेति॑ परि - च॒राय॑ ।",
         "अर॑ण्याना॒म् पत॑ये॒ पत॒ये ऽर॑ण्याना॒ मर॑ण्याना॒म् पत॑ये॒ नमो॒ नम॒ स्पत॒ये ऽर॑ण्याना॒ मर॑ण्याना॒म् पत॑ये॒ नमः॑ ।",
         "पत॑ये॒ नमो॒ नम॒ स्पत॑ये॒ पत॑ये॒ नमो॒ नमः॑ ।",
         "नमो॒ नमः॑ ।",
         "नमः॑ सृका॒विभ्यः॑ सृका॒विभ्यो॒ नमो॒ नमः॑ सृका॒विभ्यो॒ जिघाꣳ॑सद्भ्यो॒ जिघाꣳ॑सद्भ्यः सृका॒विभ्यो॒ नमो॒ नमः॑ सृका॒विभ्यो॒ जिघाꣳ॑सद्भ्यः ।",
         "सृ॒का॒विभ्यो॒ जिघाꣳ॑सद्भ्यो॒ जिघाꣳ॑सद्भ्यः सृका॒विभ्यः॑ सृका॒विभ्यो॒ जिघाꣳ॑सद्भ्यो मुष्ण॒ताम् मु॑ष्ण॒ताम् जिघाꣳ॑सद्भ्यः सृका॒विभ्यः॑ सृका॒विभ्यो॒ जिघाꣳ॑सद्भ्यो मुष्ण॒ताम् ।",
         "सृ॒का॒विभ्य॒ इति॑ सृका॒वि - भ्यः॒ ।",
         "जिघाꣳ॑सद्भ्यो मुष्ण॒ताम् मु॑ष्ण॒ताम् जिघाꣳ॑सद्भ्यो॒ जिघाꣳ॑सद्भ्यो मुष्ण॒ताम् पत॑ये॒ पत॑ये मुष्ण॒ताम् जिघाꣳ॑सद्भ्यो॒ जिघाꣳ॑सद्भ्यो मुष्ण॒ताम् पत॑ये ।",
         "जिघाꣳ॑सद्भ्य॒ इति॒ जिघाꣳ॑सत् - भ्यः॒ ।",
         "मु॒ष्ण॒ताम् पत॑ये॒ पत॑ये मुष्ण॒ताम् मु॑ष्ण॒ताम् पत॑ये॒ नमो॒ नम॒ स्पत॑ये मुष्ण॒ताम् मु॑ष्ण॒ताम् पत॑ये॒ नमः॑ ।",
         "पत॑ये॒ नमो॒ नम॒ स्पत॑ये॒ पत॑ये॒ नमो॒ नमः॑ ।",
         "नमो॒ नमः॑ ।",
         "नमो॑ ऽसि॒मद्भ्यो॑ ऽसि॒मद्भ्यो॒ नमो॒ नमो॑ ऽसि॒मद्भ्यो॒ नक्त॒म् नक्त॑ मसि॒मद्भ्यो॒ नमो॒ नमो॑ ऽसि॒मद्भ्यो॒ नक्त᳚म् ।",
         "अ॒सि॒मद्भ्यो॒ नक्त॒म् नक्त॑ मसि॒मद्भ्यो॑ ऽसि॒मद्भ्यो॒ नक्त॒म् चर॑द्भ्य॒ श्चर॑द्भ्यो॒ नक्त॑ मसि॒मद्भ्यो॑ ऽसि॒मद्भ्यो॒ नक्त॒म् चर॑द्भ्यः ।",
         "अ॒सि॒मद्भ्य॒ इत्य॑सि॒मत् - भ्यः॒ ।",
         "नक्त॒म् चर॑द्भ्य॒ श्चर॑द्भ्यो॒ नक्त॒म् नक्त॒म् चर॑द्भ्यः प्रकृ॒न्ताना᳚म् प्रकृ॒न्ताना॒म् चर॑द्भ्यो॒ नक्त॒म् नक्त॒म् चर॑द्भ्यः प्रकृ॒न्ताना᳚म् ।",
         "चर॑द्भ्यः प्रकृ॒न्ताना᳚म् प्रकृ॒न्ताना॒म् चर॑द्भ्य॒ श्चर॑द्भ्यः प्रकृ॒न्ताना॒म् पत॑ये॒ पत॑ये प्रकृ॒न्ताना॒म् चर॑द्भ्य॒ श्चर॑द्भ्यः प्रकृ॒न्ताना॒म् पत॑ये ।",
         "चर॑द्भ्य॒ इति॒ चर॑त् - भ्यः॒ ।",
         "प्र॒कृ॒न्ताना॒म् पत॑ये॒ पत॑ये प्रकृ॒न्ताना᳚म् प्रकृ॒न्ताना॒म् पत॑ये॒ नमो॒ नम॒ स्पत॑ये प्रकृ॒न्ताना᳚म् प्रकृ॒न्ताना॒म् पत॑ये॒ नमः॑ ।",
         "प्र॒कृ॒न्ताना॒मिति॑ प्र - कृ॒न्ताना᳚म् ।",
         "पत॑ये॒ नमो॒ नम॒ स्पत॑ये॒ पत॑ये॒ नमो॒ नमः॑ ।",
         "नमो॒ नमः॑ ।",
         "नम॑ उष्णी॒षिण॑ उष्णी॒षिणे॒ नमो॒ नम॑ उष्णी॒षिणे॑ गिरिच॒राय॑ गिरिच॒रा यो᳚ष्णी॒षिणे॒ नमो॒ नम॑ उष्णी॒षिणे॑ गिरिच॒राय॑ ।",
         "उ॒ष्णी॒षिणे॑ गिरिच॒राय॑ गिरिच॒रा यो᳚ष्णी॒षिण॑ उष्णी॒षिणे॑ गिरिच॒राय॑ कुलु॒ञ्चाना᳚म् कुलु॒ञ्चाना᳚म् गिरिच॒रा यो᳚ष्णी॒षिण॑ उष्णी॒षिणे॑ गिरिच॒राय॑ कुलु॒ञ्चाना᳚म् ।",
         "गि॒रि॒च॒राय॑ कुलु॒ञ्चाना᳚म् कुलु॒ञ्चाना᳚म् गिरिच॒राय॑ गिरिच॒राय॑ कुलु॒ञ्चाना॒म् पत॑ये॒ पत॑ये कुलु॒ञ्चाना᳚म् गिरिच॒राय॑ गिरिच॒राय॑ कुलु॒ञ्चाना॒म् पत॑ये ।",
         "गि॒रि॒च॒रायेति॑ गिरि - च॒राय॑ ।",
         "कु॒लु॒ञ्चाना॒म् पत॑ये॒ पत॑ये कुलु॒ञ्चाना᳚म् कुलु॒ञ्चाना॒म् पत॑ये॒ नमो॒ नम॒ स्पत॑ये कुलु॒ञ्चाना᳚म् कुलु॒ञ्चाना॒म् पत॑ये॒ नमः॑ ।",
         "पत॑ये॒ नमो॒ नम॒ स्पत॑ये॒ पत॑ये॒ नमो॒ नमः॑ ।",
         "नमो॒ नमः॑ ।",
         "नम॒ इषु॑मद्भ्य॒ इषु॑मद्भ्यो॒ नमो॒ नम॒ इषु॑मद्भ्यो धन्वा॒विभ्यो॑ धन्वा॒विभ्य॒ इषु॑मद्भ्यो॒ नमो॒ नम॒ इषु॑मद्भ्यो धन्वा॒विभ्यः॑ ।"
      ]
   },
   "id": "TS 4.5.3.1",
   "jataipaatha": {
      "lines": [
         "नमः॒ सह॑मानाय॒ सह॑मानाय॒ नमो॒ नमः॒ सह॑मानाय ।",
         "सह॑मानाय निव्या॒धिने॑ निव्या॒धिने॒ सह॑मानाय॒ सह॑मानाय निव्या॒धिने᳚ ।",
         "नि॒व्या॒धिन॑ आव्या॒धिनी॑ना माव्या॒धिनी॑ना न्निव्या॒धिने॑ निव्या॒धिन॑ आव्या॒धिनी॑नाम् ।",
         "नि॒व्या॒धिन॒ इति॑ नि - व्या॒धिने᳚ ।",
         "आ॒व्या॒धिनी॑ना॒म् पत॑ये॒ पत॑य आव्या॒धिनी॑ना माव्या॒धिनी॑ना॒म् पत॑ये ।",
         "आ॒व्या॒धिनी॑ना॒मित्या᳚ - व्या॒धिनी॑नाम् ।",
         "पत॑ये॒ नमो॒ नम॒ स्पत॑ये॒ पत॑ये॒ नमः॑ ।",
         "नमो॒ नमः॑ ।",
         "नमः॑ ककु॒भाय॑ ककु॒भाय॒ नमो॒ नमः॑ ककु॒भाय॑ ।",
         "क॒कु॒भाय॑ निष॒ङ्गिणे॑ निष॒ङ्गिणे॑ ककु॒भाय॑ ककु॒भाय॑ निष॒ङ्गिणे᳚ ।",
         "नि॒ष॒ङ्गिणे᳚ स्ते॒नाना(ग्ग्॑) स्ते॒नाना᳚ न्निष॒ङ्गिणे॑ निष॒ङ्गिणे᳚ स्ते॒नाना᳚म् ।",
         "नि॒ष॒ङ्गिण॒ इति॑ नि - स॒ङ्गिने᳚ ।",
         "स्ते॒नाना॒म् पत॑ये॒ पत॑ये स्ते॒नाना(ग्ग्॑) स्ते॒नाना॒म् पत॑ये ।",
         "पत॑ये॒ नमो॒ नम॒ स्पत॑ये॒ पत॑ये॒ नमः॑ ।",
         "नमो॒ नमः॑ ।",
         "नमो॑ निष॒ङ्गिणे॑ निष॒ङ्गिणे॒ नमो॒ नमो॑ निष॒ङ्गिणे᳚ ।",
         "नि॒ष॒ङ्गिण॑ इषुधि॒मत॑ इषुधि॒मते॑ निष॒ङ्गिणे॑ निष॒ङ्गिण॑ इषुधि॒मते᳚ ।",
         "नि॒ष॒ङ्गिण॒ इति॑ नि - स॒ङ्गिने᳚ ।",
         "इ॒षु॒धि॒मते॒ तस्क॑राणा॒म् तस्क॑राणा मिषुधि॒मत॑ इषुधि॒मते॒ तस्क॑राणाम् ।",
         "इ॒षु॒धि॒मत॒ इती॑षुधि - मते᳚ ।",
         "तस्क॑राणा॒म् पत॑ये॒ पत॑ये॒ तस्क॑राणा॒म् तस्क॑राणा॒म् पत॑ये ।",
         "पत॑ये॒ नमो॒ नम॒ स्पत॑ये॒ पत॑ये॒ नमः॑ ।",
         "नमो॒ नमः॑ ।",
         "नमो॒ वञ्च॑ते॒ वञ्च॑ते॒ नमो॒ नमो॒ वञ्च॑ते ।",
         "वञ्च॑ते परि॒वञ्च॑ते परि॒वञ्च॑ते॒ वञ्च॑ते॒ वञ्च॑ते परि॒वञ्च॑ते ।",
         "प॒रि॒वञ्च॑ते स्तायू॒नाꣳ स्ता॑यू॒नाम् प॑रि॒वञ्च॑ते परि॒वञ्च॑ते स्तायू॒नाम् ।",
         "प॒रि॒वञ्च॑त॒ इति॑ परि - वञ्च॑ते ।",
         "स्ता॒यू॒नाम् पत॑ये॒ पत॑ये स्तायू॒नाꣳ स्ता॑यू॒नाम् पत॑ये ।",
         "पत॑ये॒ नमो॒ नम॒ स्पत॑ये॒ पत॑ये॒ नमः॑ ।",
         "नमो॒ नमः॑ ।",
         "नमो॑ निचे॒रवे॑ निचे॒रवे॒ नमो॒ नमो॑ निचे॒रवे᳚ ।",
         "नि॒चे॒रवे॑ परिच॒राय॑ परिच॒राय॑ निचे॒रवे॑ निचे॒रवे॑ परिच॒राय॑ ।",
         "नि॒चे॒रव॒ इति॑ नि - चे॒रवे᳚ ।",
         "प॒रि॒च॒राया र॑ण्याना॒ मर॑ण्यानाम् परिच॒राय॑ परिच॒राया र॑ण्यानाम् ।",
         "प॒रि॒च॒रायेति॑ परि - च॒राय॑ ।",
         "अर॑ण्याना॒म् पत॑ये॒ पत॒ये ऽर॑ण्याना॒ मर॑ण्याना॒म् पत॑ये ।",
         "पत॑ये॒ नमो॒ नम॒ स्पत॑ये॒ पत॑ये॒ नमः॑ ।",
         "नमो॒ नमः॑ ।",
         "नमः॑ सृका॒विभ्यः॑ सृका॒विभ्यो॒ नमो॒ नमः॑ सृका॒विभ्यः॑ ।",
         "सृ॒का॒विभ्यो॒ जिघा(ग्म्॑)सद्भ्यो॒ जिघा(ग्म्॑)सद्भ्यः सृका॒विभ्यः॑ सृका॒विभ्यो॒ जिघा(ग्म्॑)सद्भ्यः ।",
         "सृ॒का॒विभ्य॒ इति॑ सृका॒वि - भ्यः॒ ।",
         "जिघा(ग्म्॑)सद्भ्यो मुष्ण॒ताम् मु॑ष्ण॒ताम् जिघा(ग्म्॑)सद्भ्यो॒ जिघा(ग्म्॑)सद्भ्यो मुष्ण॒ताम् ।",
         "जिघा(ग्म्॑)सद्भ्य॒ इति॒ जिघा(ग्म्॑)सत् - भ्यः॒ ।",
         "मु॒ष्ण॒ताम् पत॑ये॒ पत॑ये मुष्ण॒ताम् मु॑ष्ण॒ताम् पत॑ये ।",
         "पत॑ये॒ नमो॒ नम॒ स्पत॑ये॒ पत॑ये॒ नमः॑ ।",
         "नमो॒ नमः॑ ।",
         "नमो॑ ऽसि॒मद्भ्यो॑ ऽसि॒मद्भ्यो॒ नमो॒ नमो॑ ऽसि॒मद्भ्यः॑ ।",
         "अ॒सि॒मद्भ्यो॒ नक्त॒म् नक्त॑ मसि॒मद्भ्यो॑ ऽसि॒मद्भ्यो॒ नक्त᳚म् ।",
         "अ॒सि॒मद्भ्य॒ इत्य॑सि॒मत् - भ्यः॒ ।",
         "नक्त॒म् चर॑द्भ्य॒ श्चर॑द्भ्यो॒ नक्त॒म् नक्त॒म् चर॑द्भ्यः ।",
         "चर॑द्भ्यः प्रकृ॒न्ताना᳚म् प्रकृ॒न्ताना॒म् चर॑द्भ्य॒ श्चर॑द्भ्यः प्रकृ॒न्ताना᳚म् ।",
         "चर॑द्भ्य॒ इति॒ चर॑त् - भ्यः॒ ।",
         "प्र॒कृ॒न्ताना॒म् पत॑ये॒ पत॑ये प्रकृ॒न्ताना᳚म् प्रकृ॒न्ताना॒म् पत॑ये ।",
         "प्र॒कृ॒न्ताना॒मिति॑ प्र - कृ॒न्ताना᳚म् ।",
         "पत॑ये॒ नमो॒ नम॒ स्पत॑ये॒ पत॑ये॒ नमः॑ ।",
         "नमो॒ नमः॑ ।",
         "नम॑ उष्णी॒षिण॑ उष्णी॒षिणे॒ नमो॒ नम॑ उष्णी॒षिणे᳚ ।",
         "उ॒ष्णी॒षिणे॑ गिरिच॒राय॑ गिरिच॒रा यो᳚ष्णी॒षिण॑ उष्णी॒षिणे॑ गिरिच॒राय॑ ।",
         "गि॒रि॒च॒राय॑ कुलु॒ञ्चाना᳚म् कुलु॒ञ्चाना᳚म् गिरिच॒राय॑ गिरिच॒राय॑ कुलु॒ञ्चाना᳚म् ।",
         "गि॒रि॒च॒रायेति॑ गिरि - च॒राय॑ ।",
         "कु॒लु॒ञ्चाना॒म् पत॑ये॒ पत॑ये कुलु॒ञ्चाना᳚म् कुलु॒ञ्चाना॒म् पत॑ये ।",
         "पत॑ये॒ नमो॒ नम॒ स्पत॑ये॒ पत॑ये॒ नमः॑ ।",
         "नमो॒ नमः॑ ।",
         "नम॒ इषु॑मद्भ्य॒ इषु॑मद्भ्यो॒ नमो॒ नम॒ इषु॑मद्भ्यः ।"
      ]
   },
   "kramampaatha": {
      "lines": [
         "नमः॒ सह॑मानाय । सह॑मानाय निव्या॒धिने᳚ । नि॒व्या॒धिन॑ आव्या॒धिनी॑नाम् । नि॒व्या॒धिन॒ इति॑ नि - व्या॒धिने᳚ । आ॒व्या॒धिनी॑ना॒म् पत॑ये । आ॒व्या॒धिनी॑ना॒मित्या᳚ - व्या॒धिनी॑नाम् । पत॑ये॒ नमः॑ । नमो॒ नमः॑ । नमः॑ ककु॒भाय॑ । क॒कु॒भाय॑ निष॒ङ्गिणे᳚ । नि॒ष॒ङ्गिणे᳚ स्ते॒नाना᳚म् । नि॒ष॒ङ्गिण॒ इति॑ नि - स॒ङ्गिने᳚ । स्ते॒नाना॒म् पत॑ये । पत॑ये॒ नमः॑ । नमो॒ नमः॑ । नमो॑ निष॒ङ्गिणे᳚ । नि॒ष॒ङ्गिण॑ इषुधि॒मते᳚ । नि॒ष॒ङ्गिण॒ इति॑ नि - स॒ङ्गिने᳚ । इ॒षु॒धि॒मते॒ तस्क॑राणाम् । इ॒षु॒धि॒मत॒ इती॑षुधि - मते᳚ । तस्क॑राणा॒म् पत॑ये । पत॑ये॒ नमः॑ । नमो॒ नमः॑ । नमो॒ वञ्च॑ते । वञ्च॑ते परि॒वञ्च॑ते । प॒रि॒वञ्च॑ते स्तायू॒नाम् । प॒रि॒वञ्च॑त॒ इति॑ परि - वञ्च॑ते । स्ता॒यू॒नां पत॑ये । पत॑ये॒ नमः॑ । नमो॒ नमः॑ । नमो॑ निचे॒रवे᳚ । नि॒चे॒रवे॑ परिच॒राय॑ । नि॒चे॒रव॒ इति॑ नि - चे॒रवे᳚ । प॒रि॒च॒रायार॑ण्यानाम् । प॒रि॒च॒रायेति॑ परि - च॒राय॑ । अर॑ण्याना॒म् पत॑ये । पत॑ये॒ नमः॑ । नमो॒ नमः॑ । नमः॑ सृका॒विभ्यः॑ । सृ॒का॒विभ्यो॒ जिघाꣳ॑सद्भ्यः । सृ॒का॒विभ्य॒ इति॑ सृका॒वि - भ्यः॒ । जिघाꣳ॑सद्भ्यो मुष्ण॒ताम् । जिघाꣳ॑सद्भ्य॒ इति॒ जिघाꣳ॑सत् - भ्यः॒ । मु॒ष्ण॒तां पत॑ये । पत॑ये॒ नमः॑ । नमो॒ नमः॑ । नमो॑ऽसि॒मद्भ्यः॑ । अ॒सि॒मद्भ्यो॒ नक्त᳚म् । अ॒सि॒मद्भ्य॒ इत्य॑सि॒मत् - भ्यः॒ । नक्त॒म् चर॑द्भ्यः । चर॑द्भ्यः प्रकृ॒न्ताना᳚म् । चर॑द्भ्य॒ इति॒ चर॑त् - भ्यः॒ । प्र॒कृ॒न्ताना॒म् पत॑ये । प्र॒कृ॒न्ताना॒मिति॑ प्र - कृ॒न्ताना᳚म् । पत॑ये॒ नमः॑ । नमो॒ नमः॑ । नम॑ उष्णी॒षिणे᳚ । उ॒ष्णी॒षिणे॑ गिरिच॒राय॑ । गि॒रि॒च॒राय॑ कुलु॒ञ्चाना᳚म् । गि॒रि॒च॒रायेति॑ गिरि - च॒राय॑ । कु॒लु॒ञ्चाना॒म् पत॑ये । पत॑ये॒ नमः॑ । नमो॒ नमः॑ । नम॒ इषु॑मद्भ्यः"
      ]
   },
   "padapaatha": {
      "lines": [
         "नमः॑ । सह॑मानाय । नि॒व्या॒धिन॒ इति॑ नि - व्या॒धिने᳚ । आ॒व्या॒धिनी॑ना॒मित्या᳚ - व्या॒धिनी॑नाम् । पत॑ये । नमः॑ । नमः॑ । क॒कु॒भाय॑ । नि॒ष॒ङ्गिण॒ इति॑ नि-स॒ङ्गिने᳚ । स्ते॒नाना᳚म् । पत॑ये । नमः॑ । नमः॑ । नि॒ष॒ङ्गिण॒ इति॑ नि - स॒ङ्गिने᳚ । इ॒षु॒धि॒मत इती॑षुधि - मते᳚ । तस्क॑राणाम् । पत॑ये । नमः॑ । नमः॑ । वञ्च॑ते । प॒रि॒वञ्च॑त॒ इति॑ परि - वञ्च॑ते । स्ता॒यू॒नाम् । पत॑ये । नमः॑ । नमः॑ । नि॒चे॒रव॒ इति॑ नि - चे॒रवे᳚ । प॒रि॒च॒रायेति॑ परि - च॒राय॑ । अर॑ण्यानाम् । पत॑ये । नमः॑ । नमः॑ । सृ॒का॒विभ्य॒ इति॑ सृका॒वि - भ्यः॒ । जिघाꣳ॑सद्भ्य॒ इति॒ जिघाꣳ॑सत् - भ्यः॒ । मु॒ष्ण॒ताम् । पत॑ये । नमः॑ । नमः॑ । अ॒सि॒मद्भ्य॒ इत्य॑सि॒मत् - भ्यः॒ । नक्त᳚म् । चर॑द्भ्य॒ इति॒ चर॑त् - भ्यः॒ । प्र॒कृ॒न्ताना॒मिति॑ प्र - कृ॒न्ताना᳚म् । पत॑ये । नमः॑ । नमः॑ । उ॒ष्णी॒षिणे᳚ । गि॒रि॒च॒रायेति॑ गिरि - च॒राय॑ । कु॒लु॒ञ्चाना᳚म् । पत॑ये । नमः॑ । नमः॑ ।"
      ]
   },
   "samhita": {
      "lines": [
         "नमः॒ सह॑मानाय निव्या॒धिन॑ आव्या॒धिनी॑नां॒ पत॑ये॒ नमो॒          नमः॑ ककु॒भाय॑ निष॒ङ्गिणे᳚ स्ते॒नानां॒ पत॑ये॒ नमो॒                       नमो॑ निष॒ङ्गिण॑ इषुधि॒मते॒ तस्क॑राणां॒ पत॑ये॒ नमो॒           नमो॒ वञ्च॑ते परि॒वञ्च॑ते स्तायू॒नां पत॑ये॒ नमो॒                                         नमो॑ निचे॒रवे॑ परिच॒रायार॑ण्यानां॒ पत॑ये॒ नमो॒                                   नमः॑ सृका॒विभ्यो॒ जिघाꣳ॑सद्भ्यो मुष्ण॒तां पत॑ये॒ नमो॒                   नमो॑ ऽसि॒मद्भ्यो॒ नक्तं॒ चर॑द्भ्यः प्रकृ॒न्तानां॒ पत॑ये॒ नमो॒ नम॑ उष्णी॒षिणे॑ गिरिच॒राय॑ कुलु॒ञ्चानां॒ पत॑ये॒ नमो॒ नम॒ - [  ]"
      ]
   }
}