{
   "attribute": {
      "chandas": "",
      "devata": "",
      "rishi": ""
   },
   "classification": {
      "anuvakkam": 6,
      "kanda": 1,
      "panchasat": 1,
      "prasna": 8
   },
   "ghanapaatha": {
      "lines": [
         "प्र॒ति॒पू॒रु॒ष मेक॑कपाला॒ नेक॑कपालान् प्रतिपूरु॒षम् प्र॑तिपूरु॒ष मेक॑कपाला॒न् निर् णिरेक॑कपालान् प्रतिपूरु॒षम् प्र॑तिपूरु॒ष मेक॑कपाला॒न् निः ।",
         "प्र॒ति॒पू॒रु॒षमिति॑ प्रति - पू॒रु॒षम् ।",
         "एक॑कपाला॒न् निर् णिरेक॑कपाला॒ नेक॑कपाला॒न् निर् व॑पति वपति॒ निरेक॑कपाला॒ नेक॑कपाला॒न् निर् व॑पति ।",
         "एक॑कपाला॒नित्येक॑ - क॒पा॒ला॒न् ।",
         "निर् व॑पति वपति॒ निर् णिर् व॑प॒ त्येक॒ मेकं॑ ॅवपति॒ निर् णिर् व॑प॒ त्येक᳚म् ।",
         "व॒प॒ त्येक॒ मेकं॑ ॅवपति वप॒ त्येक॒ मति॑रिक्त॒ मति॑रिक्त॒ मेकं॑ ॅवपति वप॒ त्येक॒ मति॑रिक्तम् ।",
         "एक॒ मति॑रिक्त॒ मति॑रिक्त॒ मेक॒ मेक॒ मति॑रिक्तं॒ ॅयाव॑न्तो॒ याव॒न्तो ऽति॑रिक्त॒ मेक॒ मेक॒ मति॑रिक्तं॒ ॅयाव॑न्तः ।",
         "अति॑रिक्तं॒ ॅयाव॑न्तो॒ याव॒न्तो ऽति॑रिक्त॒ मति॑रिक्तं॒ ॅयाव॑न्तो गृ॒ह्या॑ गृ॒ह्या॑ याव॒न्तो ऽति॑रिक्त॒ मति॑रिक्तं॒ ॅयाव॑न्तो गृ॒ह्याः᳚ ।",
         "अति॑रिक्त॒मित्यति॑ - रि॒क्त॒म् ।",
         "याव॑न्तो गृ॒ह्या॑ गृ॒ह्या॑ याव॑न्तो॒ याव॑न्तो गृ॒ह्याः᳚ स्मः स्मो गृ॒ह्या॑ याव॑न्तो॒ याव॑न्तो गृ॒ह्याः᳚ स्मः ।",
         "गृ॒ह्याः᳚ स्मः स्मो गृ॒ह्या॑ गृ॒ह्याः᳚ स्म स्तेभ्य॒ स्तेभ्यः॒ स्मो गृ॒ह्या॑ गृ॒ह्याः᳚ स्म स्तेभ्यः॑ ।",
         "स्म स्तेभ्य॒ स्तेभ्यः॒ स्मः स्म स्तेभ्यः॒ कम् कम् तेभ्यः॒ स्मः स्म स्तेभ्यः॒ कम् ।",
         "तेभ्यः॒ कम् कम् तेभ्य॒ स्तेभ्यः॒ क म॑कर मकर॒म् कम् तेभ्य॒ स्तेभ्यः॒ क म॑करम् ।",
         "क म॑कर मकर॒म् कम् क म॑करम् पशू॒नाम् प॑शू॒ना म॑कर॒म् कम् क म॑करम् पशू॒नाम् ।",
         "अ॒क॒र॒म् प॒शू॒नाम् प॑शू॒ना म॑कर मकरम् पशू॒नाꣳ शर्म॒ शर्म॑ पशू॒ना म॑कर मकरम् पशू॒नाꣳ शर्म॑ ।",
         "प॒शू॒नाꣳ शर्म॒ शर्म॑ पशू॒नाम् प॑शू॒नाꣳ शर्मा᳚स्यसि॒ शर्म॑ पशू॒नाम् प॑शू॒नाꣳ शर्मा॑सि ।",
         "शर्मा᳚स्यसि॒ शर्म॒ शर्मा॑सि॒ शर्म॒ शर्मा॑सि॒ शर्म॒ शर्मा॑सि॒ शर्म॑ ।",
         "अ॒सि॒ शर्म॒ शर्मा᳚स्यसि॒ शर्म॒ यज॑मानस्य॒ यज॑मानस्य॒ शर्मा᳚स्यसि॒ शर्म॒ यज॑मानस्य ।",
         "शर्म॒ यज॑मानस्य॒ यज॑मानस्य॒ शर्म॒ शर्म॒ यज॑मानस्य॒ शर्म॒ शर्म॒ यज॑मानस्य॒ शर्म॒ शर्म॒ यज॑मानस्य॒ शर्म॑ ।",
         "यज॑मानस्य॒ शर्म॒ शर्म॒ यज॑मानस्य॒ यज॑मानस्य॒ शर्म॑ मे मे॒ शर्म॒ यज॑मानस्य॒ यज॑मानस्य॒ शर्म॑ मे ।",
         "शर्म॑ मे मे॒ शर्म॒ शर्म॑ मे यच्छ यच्छ मे॒ शर्म॒ शर्म॑ मे यच्छ ।",
         "मे॒ य॒च्छ॒ य॒च्छ॒ मे॒ मे॒ य॒च्छैक॒ एको॑ यच्छ मे मे य॒च्छैकः॑ ।",
         "य॒च्छैक॒ एको॑ यच्छ य॒च्छैक॑ ए॒वै वैको॑ यच्छ य॒च्छैक॑ ए॒व ।",
         "एक॑ ए॒वै वैक॒ एक॑ ए॒व रु॒द्रो रु॒द्र ए॒वैक॒ एक॑ ए॒व रु॒द्रः ।",
         "ए॒व रु॒द्रो रु॒द्र ए॒वैव रु॒द्रो न न रु॒द्र ए॒वैव रु॒द्रो न ।",
         "रु॒द्रो न न रु॒द्रो रु॒द्रो न द्वि॒तीया॑य द्वि॒तीया॑य॒ न रु॒द्रो रु॒द्रो न द्वि॒तीया॑य ।",
         "न द्वि॒तीया॑य द्वि॒तीया॑य॒ न न द्वि॒तीया॑य तस्थे तस्थे द्वि॒तीया॑य॒ न न द्वि॒तीया॑य तस्थे ।",
         "द्वि॒तीया॑य तस्थे तस्थे द्वि॒तीया॑य द्वि॒तीया॑य तस्थ आ॒खु रा॒खु स्त॑स्थे द्वि॒तीया॑य द्वि॒तीया॑य तस्थ आ॒खुः ।",
         "त॒स्थ॒ आ॒खु रा॒खु स्त॑स्थे तस्थ आ॒खु स्ते॑ त आ॒खु स्त॑स्थे तस्थ आ॒खु स्ते᳚ ।",
         "आ॒खु स्ते॑ त आ॒खु रा॒खु स्ते॑ रुद्र रुद्र त आ॒खु रा॒खु स्ते॑ रुद्र ।",
         "ते॒ रु॒द्र॒ रु॒द्र॒ ते॒ ते॒ रु॒द्र॒ प॒शुः प॒शू रु॑द्र ते ते रुद्र प॒शुः ।",
         "रु॒द्र॒ प॒शुः प॒शू रु॑द्र रुद्र प॒शु स्तम् तम् प॒शू रु॑द्र रुद्र प॒शु स्तम् ।",
         "प॒शु स्तम् तम् प॒शुः प॒शु स्तम् जु॑षस्व जुषस्व॒ तम् प॒शुः प॒शु स्तम् जु॑षस्व ।",
         "तम् जु॑षस्व जुषस्व॒ तम् तम् जु॑षस्वै॒ष ए॒ष जु॑षस्व॒ तम् तम् जु॑षस्वै॒षः ।",
         "जु॒ष॒ स्वै॒ष ए॒ष जु॑षस्व जुष स्वै॒ष ते॑ त ए॒ष जु॑षस्व जुष स्वै॒ष ते᳚ ।",
         "ए॒ष ते॑ त ए॒ष ए॒ष ते॑ रुद्र रुद्र त ए॒ष ए॒ष ते॑ रुद्र ।",
         "ते॒ रु॒द्र॒ रु॒द्र॒ ते॒ ते॒ रु॒द्र॒ भा॒गो भा॒गो रु॑द्र ते ते रुद्र भा॒गः ।",
         "रु॒द्र॒ भा॒गो भा॒गो रु॑द्र रुद्र भा॒गः स॒ह स॒ह भा॒गो रु॑द्र रुद्र भा॒गः स॒ह ।",
         "भा॒गः स॒ह स॒ह भा॒गो भा॒गः स॒ह स्वस्रा॒ स्वस्रा॑ स॒ह भा॒गो भा॒गः स॒ह स्वस्रा᳚ ।",
         "स॒ह स्वस्रा॒ स्वस्रा॑ स॒ह स॒ह स्वस्रा ऽम्बि॑क॒या ऽम्बि॑कया॒ स्वस्रा॑ स॒ह स॒ह स्वस्रा ऽम्बि॑कया ।",
         "स्वस्रा ऽम्बि॑क॒या ऽम्बि॑कया॒ स्वस्रा॒ स्वस्रा ऽम्बि॑कया॒ तम् त मम्बि॑कया॒ स्वस्रा॒ स्वस्रा ऽम्बि॑कया॒ तम् ।",
         "अम्बि॑कया॒ तम् त मम्बि॑क॒या ऽम्बि॑कया॒ तम् जु॑षस्व जुषस्व॒ त मम्बि॑क॒या ऽम्बि॑कया॒ तम् जु॑षस्व ।",
         "तम् जु॑षस्व जुषस्व॒ तम् तम् जु॑षस्व भेष॒जम् भे॑ष॒जम् जु॑षस्व॒ तम् तम् जु॑षस्व भेष॒जम् ।",
         "जु॒ष॒स्व॒ भे॒ष॒जम् भे॑ष॒जम् जु॑षस्व जुषस्व भेष॒जम् गवे॒ गवे॑ भेष॒जम् जु॑षस्व जुषस्व भेष॒जम् गवे᳚ ।",
         "भे॒ष॒जम् गवे॒ गवे॑ भेष॒जम् भे॑ष॒जम् गवे ऽश्वा॒या श्वा॑य॒ गवे॑ भेष॒जम् भे॑ष॒जम् गवे ऽश्वा॑य ।",
         "गवे ऽश्वा॒या श्वा॑य॒ गवे॒ गवे ऽश्वा॑य॒ पुरु॑षाय॒ पुरु॑षा॒ याश्वा॑य॒ गवे॒ गवे ऽश्वा॑य॒ पुरु॑षाय ।",
         "अश्वा॑य॒ पुरु॑षाय॒ पुरु॑षा॒ याश्वा॒ याश्वा॑य॒ पुरु॑षाय भेष॒जम् भे॑ष॒जम् पुरु॑षा॒या श्वा॒या श्वा॑य॒ पुरु॑षाय भेष॒जम् ।",
         "पुरु॑षाय भेष॒जम् भे॑ष॒जम् पुरु॑षाय॒ पुरु॑षाय भेष॒ज मथो॒ अथो॑ भेष॒जम् पुरु॑षाय॒ पुरु॑षाय भेष॒ज मथो᳚ ।",
         "भे॒ष॒ज मथो॒ अथो॑ भेष॒जम् भे॑ष॒ज मथो॑ अ॒स्मभ्य॑ म॒स्मभ्य॒ मथो॑ भेष॒जम् भे॑ष॒ज मथो॑ अ॒स्मभ्य᳚म् ।",
         "अथो॑ अ॒स्मभ्य॑ म॒स्मभ्य॒ मथो॒ अथो॑ अ॒स्मभ्य॑म् भेष॒जम् भे॑ष॒ज म॒स्मभ्य॒ मथो॒ अथो॑ अ॒स्मभ्य॑म् भेष॒जम् ।",
         "अथो॒ इत्यथो᳚ ।",
         "अ॒स्मभ्य॑म् भेष॒जम् भे॑ष॒ज म॒स्मभ्य॑ म॒स्मभ्य॑म् भेष॒जꣳ सुभे॑षजꣳ॒॒ सुभे॑षजम् भेष॒ज म॒स्मभ्य॑ म॒स्मभ्य॑म् भेष॒जꣳ सुभे॑षजम् ।",
         "अ॒स्मभ्य॒मित्य॒स्म - भ्य॒म् ।",
         "भे॒ष॒जꣳ सुभे॑षजꣳ॒॒ सुभे॑षजम् भेष॒जम् भे॑ष॒जꣳ सुभे॑षजं॒ ॅयथा॒ यथा॒ सुभे॑षजम् भेष॒जम् भे॑ष॒जꣳ सुभे॑षजं॒ ॅयथा᳚ ।",
         "सुभे॑षजं॒ ॅयथा॒ यथा॒ सुभे॑षजꣳ॒॒ सुभे॑षजं॒ ॅयथा ऽस॒त्यस॑ति॒ यथा॒ सुभे॑षजꣳ॒॒ सुभे॑षजं॒ ॅयथा ऽस॑ति ।",
         "सुभे॑षज॒मिति॒ सु - भे॒ष॒ज॒म् ।"
      ]
   },
   "id": "TS 1.8.6.1",
   "jataipaatha": {
      "lines": [
         "प्र॒ति॒पू॒रु॒ष मेक॑कपाला॒ नेक॑कपालान् प्रतिपूरु॒षम् प्र॑तिपूरु॒ष मेक॑कपालान् ।",
         "प्र॒ति॒पू॒रु॒षमिति॑ प्रति - पू॒रु॒षम् ।",
         "एक॑कपाला॒न् निर् णिरेक॑कपाला॒ नेक॑कपाला॒न् निः ।",
         "एक॑कपाला॒नित्येक॑ - क॒पा॒ला॒न् ।",
         "निर् व॑पति वपति॒ निर् णिर् व॑पति ।",
         "व॒प॒त्येक॒ मेकं॑ ॅवपति वप॒त्येक᳚म् ।",
         "एक॒ मति॑रिक्त॒ मति॑रिक्त॒ मेक॒ मेक॒ मति॑रिक्तम् ।",
         "अति॑रिक्तं॒ ॅयाव॑न्तो॒ याव॒न्तो ऽति॑रिक्त॒ मति॑रिक्तं॒ ॅयाव॑न्तः ।",
         "अति॑रिक्त॒मित्यति॑ - रि॒क्त॒म् ।",
         "याव॑न्तो गृ॒ह्या॑ गृ॒ह्या॑ याव॑न्तो॒ याव॑न्तो गृ॒ह्याः᳚ ।",
         "गृ॒ह्याः᳚ स्मः स्मो गृ॒ह्या॑ गृ॒ह्याः᳚ स्मः ।",
         "स्म स्तेभ्य॒ स्तेभ्यः॒ स्मः स्म स्तेभ्यः॑ ।",
         "तेभ्यः॒ कम् कम् तेभ्य॒ स्तेभ्यः॒ कम् ।",
         "क म॑कर मकर॒म् कम् क म॑करम् ।",
         "अ॒क॒र॒म् प॒शू॒नाम् प॑शू॒ना म॑कर मकरम् पशू॒नाम् ।",
         "प॒शू॒नाꣳ शर्म॒ शर्म॑ पशू॒नाम् प॑शू॒नाꣳ शर्म॑ ।",
         "शर्मा᳚स्यसि॒ शर्म॒ शर्मा॑सि ।",
         "अ॒सि॒ शर्म॒ शर्मा᳚स्यसि॒ शर्म॑ ।",
         "शर्म॒ यज॑मानस्य॒ यज॑मानस्य॒ शर्म॒ शर्म॒ यज॑मानस्य ।",
         "यज॑मानस्य॒ शर्म॒ शर्म॒ यज॑मानस्य॒ यज॑मानस्य॒ शर्म॑ ।",
         "शर्म॑ मे मे॒ शर्म॒ शर्म॑ मे ।",
         "मे॒ य॒च्छ॒ य॒च्छ॒ मे॒ मे॒ य॒च्छ॒ ।",
         "य॒च्छैक॒ एको॑ यच्छ य॒च्छैकः॑ ।",
         "एक॑ ए॒वैवैक॒ एक॑ ए॒व ।",
         "ए॒व रु॒द्रो रु॒द्र ए॒वैव रु॒द्रः ।",
         "रु॒द्रो न न रु॒द्रो रु॒द्रो न ।",
         "न द्वि॒तीया॑य द्वि॒तीया॑य॒ न न द्वि॒तीया॑य ।",
         "द्वि॒तीया॑य तस्थे तस्थे द्वि॒तीया॑य द्वि॒तीया॑य तस्थे ।",
         "त॒स्थ॒ आ॒खु रा॒खु स्त॑स्थे तस्थ आ॒खुः ।",
         "आ॒खुस्ते॑ त आ॒खु रा॒खुस्ते᳚ ।",
         "ते॒ रु॒द्र॒ रु॒द्र॒ ते॒ ते॒ रु॒द्र॒ ।",
         "रु॒द्र॒ प॒शुः प॒शू रु॑द्र रुद्र प॒शुः ।",
         "प॒शु स्तम् तम् प॒शुः प॒शु स्तम् ।",
         "तम् जु॑षस्व जुषस्व॒ तम् तम् जु॑षस्व ।",
         "जु॒ष॒स्वै॒ष ए॒ष जु॑षस्व जुषस्वै॒षः ।",
         "ए॒ष ते॑ त ए॒ष ए॒ष ते᳚ ।",
         "ते॒ रु॒द्र॒ रु॒द्र॒ ते॒ ते॒ रु॒द्र॒ ।",
         "रु॒द्र॒ भा॒गो भा॒गो रु॑द्र रुद्र भा॒गः ।",
         "भा॒गः स॒ह स॒ह भा॒गो भा॒गः स॒ह ।",
         "स॒ह स्वस्रा॒ स्वस्रा॑ स॒ह स॒ह स्वस्रा᳚ ।",
         "स्वस्रा म्बि॑क॒या म्बि॑कया॒ स्वस्रा॒ स्वस्रा म्बि॑कया ।",
         "अम्बि॑कया॒ तम् त मम्बि॑क॒या म्बि॑कया॒ तम् ।",
         "तम् जु॑षस्व जुषस्व॒ तम् तम् जु॑षस्व ।",
         "जु॒ष॒स्व॒ भे॒ष॒जम् भे॑ष॒जम् जु॑षस्व जुषस्व भेष॒जम् ।",
         "भे॒ष॒जम् गवे॒ गवे॑ भेष॒जम् भे॑ष॒जम् गवे᳚ ।",
         "गवे ऽश्वा॒या श्वा॑य॒ गवे॒ गवे ऽश्वा॑य ।",
         "अश्वा॑य॒ पुरु॑षाय॒ पुरु॑षा॒या श्वा॒या श्वा॑य॒ पुरु॑षाय ।",
         "पुरु॑षाय भेष॒जम् भे॑ष॒जम् पुरु॑षाय॒ पुरु॑षाय भेष॒जम् ।",
         "भे॒ष॒ज मथो॒ अथो॑ भेष॒जम् भे॑ष॒ज मथो᳚ ।",
         "अथो॑ अ॒स्मभ्य॑ म॒स्मभ्य॒ मथो॒ अथो॑ अ॒स्मभ्य᳚म् ।",
         "अथो॒ इत्यथो᳚ ।",
         "अ॒स्मभ्य॑म् भेष॒जम् भे॑ष॒ज म॒स्मभ्य॑ म॒स्मभ्य॑म् भेष॒जम् ।",
         "अ॒स्मभ्य॒मित्य॒स्म - भ्य॒म् ।",
         "भे॒ष॒जꣳ सुभे॑षजꣳ॒॒ सुभे॑षजम् भेष॒जम् भे॑ष॒जꣳ सुभे॑षजम् ।",
         "सुभे॑षजं॒ ॅयथा॒ यथा॒ सुभे॑षजꣳ॒॒ सुभे॑षजं॒ ॅयथा᳚ ।",
         "सुभे॑षज॒मिति॒ सु - भे॒ष॒ज॒म् ।"
      ]
   },
   "kramampaatha": {
      "lines": [
         "प्र॒ति॒पू॒रु॒षमेक॑कपालान् । प्र॒ति॒पू॒रु॒षमिति॑ प्रति - पू॒रु॒षम् । एक॑कपाला॒न् निः । एक॑कपाला॒नित्येक॑ - क॒पा॒ला॒न्॒ । निर् व॑पति । व॒प॒त्येक᳚म् । एक॒मति॑रिक्तम् । अति॑रिक्तं॒ ॅयाव॑न्तः । अति॑रिक्त॒मित्यति॑ - रि॒क्त॒म् । याव॑न्तो गृ॒ह्याः᳚ । गृ॒ह्याः᳚ स्मः । स्मस्तेभ्यः॑ । तेभ्यः॒ कम् । कम॑करम् । अ॒क॒र॒म् प॒शू॒नाम् । प॒शू॒नाꣳ शर्म॑ । शर्मा॑सि । अ॒सि॒ शर्म॑ । शर्म॒ यज॑मानस्य । यज॑मानस्य॒ शर्म॑ । शर्म॑ मे । मे॒ य॒च्छ॒ । य॒च्छैकः॑ । एक॑ ए॒व । ए॒व रु॒द्रः । रु॒द्रो न । न द्वि॒तीया॑य । द्वि॒तीया॑य तस्थे । त॒स्थ॒ आ॒खुः । आ॒खुस्ते᳚ । ते॒ रु॒द्र॒ । रु॒द्र॒ प॒शुः । प॒शुस्तम् । तम् जु॑षस्व । जु॒ष॒स्वै॒षः । ए॒ष ते᳚ । ते॒ रु॒द्र॒ । रु॒द्र॒ भा॒गः । भा॒गः स॒ह । स॒ह स्वस्रा᳚ । स्वस्राऽम्बि॑कया । अम्बि॑कया॒ तम् । तम् जु॑षस्व । जु॒ष॒स्व॒ भे॒ष॒जम् । भे॒ष॒जम् गवे᳚ । गवेऽश्वा॑य । अश्वा॑य॒ पुरु॑षाय । पुरु॑षाय भेष॒जम् । भे॒ष॒जमथो᳚ । अथो॑ अ॒स्मभ्य᳚म् । अथो॒ इत्यथो᳚ । अ॒स्मभ्य॑म् भेष॒जम् । अ॒स्मभ्य॒मित्य॒स्म - भ्य॒म् । भे॒ष॒जꣳ \nसुभे॑षजम् । सुभे॑षजं॒ ॅयथा᳚ । सुभे॑षज॒मिति॒ सु - भे॒ष॒ज॒म्"
      ]
   },
   "padapaatha": {
      "lines": [
         "प्र॒ति॒पू॒रु॒षमिति॑ प्रति-पू॒रु॒षम् । एक॑कपाला॒नित्येक॑-क॒पा॒ला॒न् । निरिति॑ । व॒प॒ति॒ । एक᳚म् । अति॑रिक्त॒मित्यति॑-रि॒क्त॒म् । याव॑न्तः । गृ॒ह्याः᳚ । स्मः । तेभ्यः॑ । कम् । अ॒क॒र॒म् । प॒शू॒नाम् । शर्म॑ । अ॒सि॒ । शर्म॑ । यज॑मानस्य । शर्म॑ । मे॒ । य॒च्छ॒ । एकः॑ । ए॒व । रु॒द्रः । न । द्वि॒तीया॑य । त॒स्थे॒ । आ॒खुः । ते॒ । रु॒द्र॒ । प॒शुः । तम् । जु॒ष॒स्व॒ । ए॒षः । ते॒ । रु॒द्र॒ । भा॒गः । स॒ह । स्वस्रा᳚ । अबिं॑कया । तम् । जु॒ष॒स्व॒ । भे॒ष॒जम् । गवे᳚ । अश्वा॑य । पुरु॑षाय । भे॒ष॒जम् । अथो॒ इति॑ । अ॒स्मभ्य॒मित्य॒स्म-भ्य॒म् । भे॒ष॒जम् । सुभे॑षज॒मिति॒ सु - भे॒ष॒ज॒म् ।"
      ]
   },
   "samhita": {
      "lines": [
         "प्र॒ति॒पू॒रु॒षमेक॑कपाला॒न् निर्व॑प॒त्येक॒-मति॑रिक्तं॒ ॅयाव॑न्तो गृ॒ह्याः᳚ स्मस्तेभ्यः॒ कम॑करं पशू॒नाꣳ शर्मा॑सि॒ शर्म॒ यज॑मानस्य॒ शर्म॑ मे य॒च्छैक॑ ए॒व रु॒द्रो न द्वि॒तीया॑य तस्थ आ॒खुस्ते॑ रुद्र प॒शुस्तं जु॑षस्वै॒ष ते॑ रुद्र भा॒गः स॒ह स्वस्राऽंबि॑कया॒ तं जु॑षस्व भेष॒जं गवेऽश्वा॑य॒ पुरु॑षाय भेष॒जमथो॑ अ॒स्मभ्यं॑ भेष॒जꣳ सुभे॑षजं॒ - [ ]"
      ]
   }
}